{
  "data": {
    "978-604-487-238-4-Overlord 2 - Chiến binh bóng tối": "Sat, 9 Nov 2024 02:09:46 +0700",
    "978-604-44-1132-3-Overlord - 6": "Sat, 9 Nov 2024 02:09:46 +0700",
    "978-604-398-042-4-Overlord 4 - Lizardman anh dũng": "Sat, 9 Nov 2024 02:09:46 +0700",
    "978-604-44-2298-5-Hành trình của Elaina tập 15": "Sat, 9 Nov 2024 01:57:57 +0700",
    "978-604-55-8439-2-Hành trình của Elaina tập 10": "Sat, 9 Nov 2024 01:57:57 +0700",
    "978-604-44-3276-2-Hành trình của Elaina tập 4": "Sat, 9 Nov 2024 02:12:33 +0700",
    "978-604-345-098-9-Nữ chính sinh tồn mạnh mẽ trong thế giới Otome Game 1": "Sat, 9 Nov 2024 02:09:42 +0700",
    "978-604-476-082-7-Overlord 7 - Những kẻ xâm nhập": "Sat, 9 Nov 2024 02:09:46 +0700",
    "978-604-44-1133-0-Overlord - 7": "Sat, 9 Nov 2024 02:09:46 +0700",
    "978-604-44-1068-5-Hành trình của Elaina tập 8": "Sat, 9 Nov 2024 01:57:57 +0700",
    "978-604-44-1129-3-Overlord - 1": "Sat, 9 Nov 2024 02:09:46 +0700",
    "978-604-359-498-0-Hành trình của Elaina tập 5": "Sat, 9 Nov 2024 01:57:57 +0700",
    "978-604-392-313-1-Cách sống của thiếu nữ hành quyết - Chỉ một màn sương trắng 2": "Tue, 12 Nov 2024 18:35:47 +0700",
    "978-604-345-544-1-Nữ chính sinh tồn mạnh mẽ trong thế giới Otome Game 2": "Sat, 9 Nov 2024 02:09:42 +0700",
    "978-604-478-149-5-Hành trình của Elaina - Tập 7": "Sat, 9 Nov 2024 01:57:57 +0700",
    "978-604-478-562-2-Hành trình của Elaina - tập 14": "Sat, 9 Nov 2024 01:57:57 +0700",
    "978-604-44-1537-6-Hành trình của Elaina - tập 1": "Sat, 9 Nov 2024 01:57:57 +0700",
    "978-604-44-1131-6-Overlord - 5": "Sat, 9 Nov 2024 02:09:46 +0700",
    "978-604-44-2012-7-Riviere và Đất nước của lời cầu nguyện - tập 1": "Sat, 9 Nov 2024 01:58:05 +0700",
    "978-604-44-2013-4-Hành trình của Elaina - tập 15": "Sat, 9 Nov 2024 01:57:57 +0700",
    "978-604-44-2300-5-Riviere và Đất nước của Lời cầu nguyện, tập 1 - Riviere and the nation of the prayer": "Sat, 9 Nov 2024 01:58:05 +0700",
    "978-604-77-7571-2-Diệt slime suốt 300 năm, tôi level MAX lúc nào chẳng hay 13": "Sat, 9 Nov 2024 02:09:36 +0700",
    "978-604-44-1130-9-Overlord - 2": "Sat, 9 Nov 2024 02:09:46 +0700",
    "978-604-55-1644-7-Hành trình của Elaina tập 13": "Sat, 9 Nov 2024 01:57:57 +0700",
    "978-604-392-470-1-Diệt slime suốt 300 năm, tôi level MAX lúc nào chẳng hay 12": "Sat, 9 Nov 2024 02:09:36 +0700",
    "978-604-77-7753-2-Cách sống của thiếu nữ hành quyết - Và rồi, cô ấy được tái sinh 1": "Tue, 12 Nov 2024 18:35:47 +0700",
    "978-604-365-363-2-Diệt slime suốt 300 năm, tôi level MAX lúc nào chẳng hay 11": "Sat, 9 Nov 2024 02:09:36 +0700",
    "978-604-77-5868-5-Nữ chính sinh tồn mạnh mẽ trong thế giới Otome Game 2": "Sat, 9 Nov 2024 02:09:42 +0700",
    "978-604-476-935-6-Overlord 8 - Hai lãnh đạo": "Sat, 9 Nov 2024 02:09:46 +0700",
    "978-604-374-605-1-Riviere và Đất nước của lời cầu nguyện": "Sat, 9 Nov 2024 01:58:05 +0700",
    "978-604-77-9568-0-Diệt slime suốt 300 năm, tôi level MAX lúc nào chẳng hay 10": "Sat, 9 Nov 2024 02:09:36 +0700",
    "978-604-487-237-7-Overlord 1 - Chúa tể bất tử": "Sat, 9 Nov 2024 02:09:46 +0700"
  },
  "title_build_date": {
    "Nữ chính sinh tồn mạnh mẽ trong thế giới Otome Game": "Sat, 9 Nov 2024 02:09:42 +0700",
    "Diệt slime suốt 300 năm, tôi level MAX lúc nào chẳng hay": "Sat, 9 Nov 2024 02:09:36 +0700",
    "Overlord": "Sat, 9 Nov 2024 02:09:46 +0700",
    "Riviere Và Đất Nước Của Lời Cầu Nguyện": "Sat, 9 Nov 2024 01:58:05 +0700",
    "Hành Trình Của Elaina": "Sat, 9 Nov 2024 02:12:33 +0700",
    "Cách sống của thiếu nữ hành quyết": "Tue, 12 Nov 2024 18:35:47 +0700"
  }
}